oarepo_vocabularies/__init__.py
oarepo_vocabularies/cli.py
oarepo_vocabularies/config.py
oarepo_vocabularies/errors.py
oarepo_vocabularies/ext.py
oarepo_vocabularies/fixtures.py
oarepo_vocabularies/for_translations_only.py
oarepo_vocabularies/hacks.py
oarepo_vocabularies/proxies.py
oarepo_vocabularies/tasks.py
oarepo_vocabularies/authorities/__init__.py
oarepo_vocabularies/authorities/components.py
oarepo_vocabularies/authorities/ext.py
oarepo_vocabularies/authorities/ext_config.py
oarepo_vocabularies/authorities/proxies.py
oarepo_vocabularies/authorities/views.py
oarepo_vocabularies/authorities/providers/__init__.py
oarepo_vocabularies/authorities/providers/base.py
oarepo_vocabularies/authorities/providers/openaire_provider.py
oarepo_vocabularies/authorities/providers/orcid_provider.py
oarepo_vocabularies/authorities/providers/ror_provider.py
oarepo_vocabularies/authorities/resources/__init__.py
oarepo_vocabularies/authorities/resources/config.py
oarepo_vocabularies/authorities/resources/resource.py
oarepo_vocabularies/models/__init__.py
oarepo_vocabularies/models/ui.json
oarepo_vocabularies/records/__init__.py
oarepo_vocabularies/records/api.py
oarepo_vocabularies/records/systemfields.py
oarepo_vocabularies/records/jsonschemas/__init__.py
oarepo_vocabularies/records/jsonschemas/vocabularies/__init__.py
oarepo_vocabularies/records/jsonschemas/vocabularies/vocabulary-ext-v1.0.0.json
oarepo_vocabularies/resources/__init__.py
oarepo_vocabularies/resources/config.py
oarepo_vocabularies/resources/ui.py
oarepo_vocabularies/resources/records/__init__.py
oarepo_vocabularies/resources/records/ui.py
oarepo_vocabularies/resources/vocabulary_type/__init__.py
oarepo_vocabularies/resources/vocabulary_type/config.py
oarepo_vocabularies/resources/vocabulary_type/resource.py
oarepo_vocabularies/services/__init__.py
oarepo_vocabularies/services/cache.py
oarepo_vocabularies/services/config.py
oarepo_vocabularies/services/facets.py
oarepo_vocabularies/services/permissions.py
oarepo_vocabularies-2.2.6.dist-info/licenses/LICENSE
oarepo_vocabularies-2.2.6.dist-info/METADATA
oarepo_vocabularies-2.2.6.dist-info/WHEEL
oarepo_vocabularies-2.2.6.dist-info/entry_points.txt
oarepo_vocabularies-2.2.6.dist-info/top_level.txt
oarepo_vocabularies-2.2.6.dist-info/RECORD
