Metadata-Version: 2.4
Name: oarepo-vocabularies
Version: 2.2.6
Summary: Support for custom fields and hierarchy on Invenio vocabularies
License-File: LICENSE
Requires-Dist: invenio-vocabularies
Requires-Dist: oarepo-runtime>=1.4.44
Requires-Dist: openpyxl
Requires-Dist: oarepo-ui>=5.0.91
Requires-Dist: cachetools
Requires-Dist: orcid
Provides-Extra: dev
Requires-Dist: pytest>=7.1.2; extra == "dev"
Requires-Dist: black; extra == "dev"
Requires-Dist: autoflake; extra == "dev"
Requires-Dist: isort; extra == "dev"
Provides-Extra: tests
Requires-Dist: pytest>=7.1.2; extra == "tests"
Requires-Dist: pytest-mock; extra == "tests"
Requires-Dist: pytest-invenio; extra == "tests"
Dynamic: license-file
